kami_gdrive/__init__.py
kami_gdrive/kami_gdrive.py
kami_gdrive-0.1.3.dist-info/METADATA
kami_gdrive-0.1.3.dist-info/WHEEL
kami_gdrive-0.1.3.dist-info/RECORD
