Metadata-Version: 2.1
Name: kami-gdrive
Version: 0.1.3
Summary: Settings to Upload files to google drive
Author: Maicon de Menezes
Author-email: maicondmenezes@gmail.com
Requires-Python: >=3.9,<4.0
Classifier: Programming Language :: Python :: 3
Classifier: Programming Language :: Python :: 3.9
Classifier: Programming Language :: Python :: 3.10
Classifier: Programming Language :: Python :: 3.11
Requires-Dist: google-api-core (>=2.11.0,<3.0.0)
Requires-Dist: google-api-python-client (>=2.50.0,<3.0.0)
Requires-Dist: google-auth (>=2.7.0,<3.0.0)
Requires-Dist: google-auth-httplib2 (>=0.1.0,<0.2.0)
Requires-Dist: google-auth-oauthlib (>=0.5.2,<0.6.0)
Requires-Dist: googleapis-common-protos (>=1.56.2,<2.0.0)
Requires-Dist: kami-logging (>=0.2.0,<0.3.0)
Requires-Dist: python-dotenv (>=1.0.0,<2.0.0)
